aio_geojson_tas_tfs_incidents/__init__.py
aio_geojson_tas_tfs_incidents/__version__.py
aio_geojson_tas_tfs_incidents/consts.py
aio_geojson_tas_tfs_incidents/feed.py
aio_geojson_tas_tfs_incidents/feed_entry.py
aio_geojson_tas_tfs_incidents/feed_manager.py
aio_geojson_tas_tfs_incidents-0.7.1.dist-info/LICENSE
aio_geojson_tas_tfs_incidents-0.7.1.dist-info/METADATA
aio_geojson_tas_tfs_incidents-0.7.1.dist-info/WHEEL
aio_geojson_tas_tfs_incidents-0.7.1.dist-info/top_level.txt
aio_geojson_tas_tfs_incidents-0.7.1.dist-info/RECORD
