Metadata-Version: 2.1
Name: aio_geojson_tas_tfs_incidents
Version: 0.7.1
Summary: An async GeoJSON client library for TAS Fire Service Incidents.
Home-page: https://github.com/zellers/python-aio-geojson-tas-tfs-incidents
Author: Malte Franken, Daniel Zeller
Author-email: geojson_tas@zeller.cx
License: Apache-2.0
Classifier: Programming Language :: Python :: 3.8
Classifier: Programming Language :: Python :: 3.9
Classifier: Programming Language :: Python :: 3.10
Classifier: Programming Language :: Python :: 3.11
Classifier: Programming Language :: Python :: 3.12
Classifier: License :: OSI Approved :: Apache Software License
Classifier: Operating System :: OS Independent
License-File: LICENSE
Requires-Dist: aio-geojson-client >=0.20
Requires-Dist: aiohttp <4,>=3.7.4
Requires-Dist: pytz >=2019.01
